libiq/__init__.py
libiq/_libiqwrapped.cpython-310-x86_64-linux-gnu.so
libiq/libiqwrapped.py
libiq/classifier/__init__.py
libiq/classifier/cnn.py
libiq/classifier/energy_detector.py
libiq/classifier/preprocessing.py
libiq/converter/__init__.py
libiq/converter/mat.py
libiq/converter/sigmf.py
libiq/plotter/__init__.py
libiq/plotter/accuracy_curve.py
libiq/plotter/confusion_matrix.py
libiq/plotter/loss_curve.py
libiq/plotter/scatterplot.py
libiq/plotter/spectrogram.py
libiq/plotter/waterfall.py
libiq/utils/__init__.py
libiq/utils/constants.py
libiq/utils/create_dataset.py
libiq/utils/logger.py
libiq.libs/libgomp-870cb1d0.so.1.0.0
libiq_swig/analyzer.cpp
libiq_swig/analyzer.h
libiq_swig/libiq_wrapped.i
libiq-0.0.2.dist-info/METADATA
libiq-0.0.2.dist-info/WHEEL
libiq-0.0.2.dist-info/top_level.txt
libiq-0.0.2.dist-info/RECORD
libiq-0.0.2.dist-info/licenses/LICENSE
