Metadata-Version: 2.4
Name: libiq
Version: 0.0.2
Summary: LibIQ is a unified Python library that provides tools for analyzing and manipulating IQ samples, along with time-series-based classification functionalities.
Author-email: Filippo Olimpieri <filippo.olimpieri@gmail.com>, Noemi Giustini <noemi.giustini.2001@gmail.com>, Andrea Lacava <thecave003@gmail.com>
License-Expression: Apache-2.0
Project-URL: Publication, https://www.arxiv.org/abs/2505.10537
Project-URL: Package, https://pypi.org/project/libiq
Project-URL: Source, https://github.com/wineslab/lib-iq
Project-URL: Bug Tracker, https://github.com/wineslab/lib-iq/issues
Requires-Python: >=3.9,<3.13
License-File: LICENSE
Requires-Dist: cython
Requires-Dist: scikit-learn
Requires-Dist: scipy
Requires-Dist: h5py
Requires-Dist: tensorflow
Requires-Dist: tslearn
Requires-Dist: yellowbrick
Requires-Dist: pandas
Requires-Dist: numpy
Requires-Dist: pydot
Requires-Dist: seaborn
Requires-Dist: pytest
Provides-Extra: report
Requires-Dist: ydata-profiling; extra == "report"
Provides-Extra: styles
Requires-Dist: SciencePlots; extra == "styles"
Provides-Extra: all
Requires-Dist: ydata-profiling; extra == "all"
Requires-Dist: SciencePlots; extra == "all"
Dynamic: license-file
Dynamic: requires-python
